aridity/__init__.py
aridity/arid_config.py
aridity/config.py
aridity/directives.py
aridity/functions.py
aridity/grammar.py
aridity/keyring.py
aridity/model.py
aridity/processtemplate.py
aridity/repl.py
aridity/resolve.py
aridity/scope.py
aridity/search.py
aridity/stacks.py
aridity/util.py
aridity-98.dist-info/METADATA
aridity-98.dist-info/WHEEL
aridity-98.dist-info/entry_points.txt
aridity-98.dist-info/top_level.txt
aridity-98.dist-info/RECORD
