Metadata-Version: 2.1
Name: aridity
Version: 98
Summary: DRY config and template system, easily extensible with Python
Home-page: https://pypi.org/project/aridity/
Author: foyono
Author-email: shrovis@foyono.com
Requires-Dist: foyndation>=14
Requires-Dist: pyparsing>=3.0.2
